async_email/__init__.py
async_email/apps.py
async_email/conf.py
async_email/exceptions.py
async_email/models.py
async_email/task.py
async_email/tasks.py
async_email/email/__init__.py
async_email/email/exceptions.py
async_email/email/tasks.py
async_email/email/template.py
async_email/email/utils.py
django_async_email-0.1.2.dist-info/LICENSE
django_async_email-0.1.2.dist-info/METADATA
django_async_email-0.1.2.dist-info/WHEEL
django_async_email-0.1.2.dist-info/top_level.txt
django_async_email-0.1.2.dist-info/RECORD
