Metadata-Version: 2.1
Name: django-async-email
Version: 0.1.2
Summary: An async Django email backend using celery
Home-page: https://github.com/eltonplima/django-async-email
Author: Elton Lima
Author-email: me@eltonplima.dev
License: Mozilla Public License 2.0
Project-URL: Changelog, https://github.com/ionelmc/python-nameless/blob/master/CHANGELOG.rst
Project-URL: Issue Tracker, https://github.com/ionelmc/python-nameless/issues
Platform: any
Classifier: Development Status :: 1 - Planning
Classifier: Framework :: Django
Classifier: Programming Language :: Python
Classifier: Programming Language :: Python :: 3
Classifier: Programming Language :: Python :: 3.7
Classifier: Programming Language :: Python :: 3.8
Classifier: Intended Audience :: Developers
Classifier: License :: OSI Approved :: BSD License
Classifier: Operating System :: POSIX
Classifier: Topic :: Communications
Classifier: Topic :: Communications :: Email
Classifier: Topic :: System :: Distributed Computing
Classifier: Topic :: Software Development :: Libraries :: Python Modules
Requires-Python: >=3.7
Requires-Dist: django (>=1.11)
Requires-Dist: celery (<5.0,>=4.2.2)
Requires-Dist: kombu (<5.0)
Requires-Dist: django-appconf
Requires-Dist: dnspython (<2.0.0,>=1.15.0)
Requires-Dist: eventlet
Provides-Extra: dev
Requires-Dist: pytest ; extra == 'dev'
Requires-Dist: pytest-pep8 ; extra == 'dev'
Requires-Dist: pytest-cov ; extra == 'dev'
Requires-Dist: pytest-mock ; extra == 'dev'
Requires-Dist: pytest-django ; extra == 'dev'
Requires-Dist: pytest-celery ; extra == 'dev'
Requires-Dist: pytest-xdist[psutil] ; extra == 'dev'
Requires-Dist: flake8 ; extra == 'dev'
Requires-Dist: black ; extra == 'dev'
Requires-Dist: isort ; extra == 'dev'
Requires-Dist: tox ; extra == 'dev'
Requires-Dist: tox-asdf ; extra == 'dev'
Requires-Dist: freezegun ; extra == 'dev'
Requires-Dist: wheel ; extra == 'dev'
